commit_msg_git_hook/__init__.py
commit_msg_git_hook/commit_msg.py
commit_msg_git_hook/scan_git.py
commit_msg_git_hook/setup.py
commit_msg_git_hook/assets/Exemplo-mensagem-inválida.png
commit_msg_git_hook/assets/Exemplo-mensagem-muito-longa.png
commit_msg_git_hook/assets/commit-msg.config.json.png
commit_msg_git_hook/templates/commit-msg.config.json
commit_msg_git_hook/templates/darwin/commit-msg
commit_msg_git_hook/templates/linux/commit-msg
commit_msg_git_hook/templates/win32/commit-msg
commit_msg_git_hook-0.7.0.dist-info/METADATA
commit_msg_git_hook-0.7.0.dist-info/WHEEL
commit_msg_git_hook-0.7.0.dist-info/licenses/LICENSE
commit_msg_git_hook-0.7.0.dist-info/RECORD
