Metadata-Version: 2.3
Name: commit_msg_git_hook
Version: 0.7.0
Summary: A set of tools to validate git Conventional Commit messages.
Project-URL: Homepage, https://github.com/OM30/commit-msg-git-hook-package
Project-URL: Bug Tracker, https://github.com/OM30/commit-msg-git-hook-package/issues
Author-email: Lucio Meira David <lucio.meira@om30.com.br>
License-File: LICENSE
Keywords: ci,commit-msg,git,git hook,git-hook,scan
Classifier: Development Status :: 4 - Beta
Classifier: Intended Audience :: Developers
Classifier: License :: OSI Approved :: MIT License
Classifier: Natural Language :: Portuguese (Brazilian)
Classifier: Operating System :: MacOS
Classifier: Operating System :: Microsoft :: Windows
Classifier: Operating System :: POSIX :: Linux
Classifier: Programming Language :: Python :: 3
Classifier: Topic :: Software Development :: Libraries :: Python Modules
Classifier: Topic :: Software Development :: Version Control :: Git
Requires-Python: >=3.7
